webinspectapi/__init__.py
webinspectapi/webinspect.py
webinspectapi-1.0.33.dist-info/LICENSE.txt
webinspectapi-1.0.33.dist-info/METADATA
webinspectapi-1.0.33.dist-info/RECORD
webinspectapi-1.0.33.dist-info/WHEEL
webinspectapi-1.0.33.dist-info/top_level.txt
webinspectapi-1.0.33.dist-info/zip-safe
