Metadata-Version: 2.1
Name: webinspectapi
Version: 1.0.33
Summary: Python library enumerating the WebInspect RESTFul API scan, securebase, and proxy endpoints.
Home-page: https://github.com/target/webinspectapi
Author: Brandon Spruth, Jim Nelson
Author-email: brandon.spruth2@target.com, jim.nelson2@target.com
License: MIT
Download-URL: https://github.com/target/webinspectapi/tarball/1.0.33
Keywords: webinspect,api,security,software,hpe,micro focus,dast
Platform: UNKNOWN
Classifier: Development Status :: 4 - Beta
Classifier: Intended Audience :: Developers
Classifier: Natural Language :: English
Classifier: License :: OSI Approved :: MIT License
Classifier: Topic :: Software Development
Classifier: Topic :: Software Development :: Libraries :: Python Modules
Classifier: Programming Language :: Python :: 2
Classifier: Programming Language :: Python :: 2.7
Classifier: Programming Language :: Python :: 3.0
Classifier: Programming Language :: Python :: 3.6
Requires-Dist: requests
